django_twilio/__init__.py
django_twilio/admin.py
django_twilio/client.py
django_twilio/decorators.py
django_twilio/exceptions.py
django_twilio/models.py
django_twilio/request.py
django_twilio/settings.py
django_twilio/utils.py
django_twilio/views.py
django_twilio/migrations/0001_initial.py
django_twilio/migrations/__init__.py
test_project/__init__.py
test_project/settings.py
test_project/urls.py
test_project/test_app/__init__.py
test_project/test_app/client.py
test_project/test_app/decorators.py
test_project/test_app/models.py
test_project/test_app/request.py
test_project/test_app/urls.py
test_project/test_app/utils.py
test_project/test_app/views.py
django_twilio-0.14.3.4.dist-info/AUTHORS
django_twilio-0.14.3.4.dist-info/METADATA
django_twilio-0.14.3.4.dist-info/WHEEL
django_twilio-0.14.3.4.dist-info/top_level.txt
django_twilio-0.14.3.4.dist-info/RECORD
