Metadata-Version: 2.1
Name: django-twilio
Version: 0.14.3.4
Summary: Build Twilio functionality into your Django apps.
Home-page: https://github.com/rdegges/django-twilio
Author: Randall Degges
Author-email: rdegges@gmail.com
Maintainer: Jason Held
Maintainer-email: jasonsheld@gmail.com
License: UNLICENSE
Project-URL: Documentation, https://django-twilio.readthedocs.io/en/latest/
Project-URL: Code, https://github.com/rdegges/django-twilio
Project-URL: Tracker, https://github.com/rdegges/django-twilio/issues
Keywords: twilio telephony call phone voip sms django django-twilio
Classifier: Framework :: Django
Classifier: Framework :: Django :: 4.0
Classifier: Framework :: Django :: 4.1
Classifier: Framework :: Django :: 5.0
Classifier: Intended Audience :: Developers
Classifier: License :: Public Domain
Classifier: Operating System :: OS Independent
Classifier: Programming Language :: Python
Classifier: Programming Language :: Python :: 3
Classifier: Programming Language :: Python :: 3 :: Only
Classifier: Programming Language :: Python :: 3.8
Classifier: Programming Language :: Python :: 3.9
Classifier: Programming Language :: Python :: 3.10
Classifier: Programming Language :: Python :: 3.11
Classifier: Programming Language :: Python :: Implementation :: CPython
Classifier: Programming Language :: Python :: Implementation :: PyPy
Classifier: Topic :: Internet :: WWW/HTTP
License-File: AUTHORS
Requires-Dist: setuptools>=36.2
Requires-Dist: twilio>=7
Requires-Dist: django-phonenumber-field>=0.6
Requires-Dist: phonenumbers>=8.10.22
Requires-Dist: Django<6,>=4.0
